fasterfva/__init__.py
fasterfva/fva.py
fasterfva-0.0.2.dist-info/LICENSE
fasterfva-0.0.2.dist-info/METADATA
fasterfva-0.0.2.dist-info/WHEEL
fasterfva-0.0.2.dist-info/top_level.txt
fasterfva-0.0.2.dist-info/RECORD
