Metadata-Version: 2.1
Name: fasterfva
Version: 0.0.2
Summary: Faster Flux Variability Analysis - Solve FVA Problems FAST
Home-page: https://github.com/DKenefake/fasterfva
Author: Dustin R. Kenefake
Author-email: Dustin.Kenefake@tamu.edu
License: MIT
Platform: UNKNOWN
License-File: LICENSE
Requires-Dist: numpy
Requires-Dist: gurobipy
